keithley2600b/__init__.py
keithley2600b-0.0.5.dist-info/METADATA
keithley2600b-0.0.5.dist-info/WHEEL
keithley2600b-0.0.5.dist-info/top_level.txt
keithley2600b-0.0.5.dist-info/RECORD
