Metadata-Version: 2.1
Name: keithley2600b
Version: 0.0.5
Summary: Python API for Keithley Series 2600B SourceMeter
Author: Kai Geissdoerfer
Author-email: kai.geissdoerfer@tu-dresden.de
License: MIT
Classifier: Development Status :: 4 - Beta
Classifier: Intended Audience :: Developers
Classifier: Intended Audience :: Information Technology
Classifier: Programming Language :: Python :: 3
Requires-Dist: numpy
Requires-Dist: pyvisa-py
